[
  {
    "@id": "alma:library:AnnenLib",
     "@type": [ "http://www.loc.gov/mads/rdf/v1#Authority" ],
     "http://www.loc.gov/mads/rdf/v1#authoritativeLabel": [ { "@value": "AnnenLib" } ]
  },
  {
    "@id": "alma:library:ArchArcLib",
    "@type": [ "http://www.loc.gov/mads/rdf/v1#Authority" ],
    "http://www.loc.gov/mads/rdf/v1#authoritativeLabel": [ { "@value": "ArchArcLib" } ]
  },
  {
    "@id": "alma:library:AreaStud",
    "@type": [ "http://www.loc.gov/mads/rdf/v1#Authority" ],
    "http://www.loc.gov/mads/rdf/v1#authoritativeLabel": [ { "@value": "AreaStud" } ]
  },
  {
    "@id": "alma:library:AthLib",
    "@type": [ "http://www.loc.gov/mads/rdf/v1#Authority" ],
    "http://www.loc.gov/mads/rdf/v1#authoritativeLabel": [ { "@value": "AthLib" } ]
  },
  {
    "@id": "alma:library:BatesCntr",
    "@type": [ "http://www.loc.gov/mads/rdf/v1#Authority" ],
    "http://www.loc.gov/mads/rdf/v1#authoritativeLabel": [ { "@value": "BatesCntr" } ]
  },
  {
    "@id": "alma:library:BiomLib",
    "@type": [ "http://www.loc.gov/mads/rdf/v1#Authority" ],
    "http://www.loc.gov/mads/rdf/v1#authoritativeLabel": [ { "@value": "BiomLib" } ]
  },
  {
    "@id": "alma:library:ChemLib",
    "@type": [ "http://www.loc.gov/mads/rdf/v1#Authority" ],
    "http://www.loc.gov/mads/rdf/v1#authoritativeLabel": [ { "@value": "ChemLib" } ]
  },
  {
    "@id": "alma:library:CHD",
    "@type": [ "http://www.loc.gov/mads/rdf/v1#Authority" ],
    "http://www.loc.gov/mads/rdf/v1#authoritativeLabel": [ { "@value": "CHD" } ]
  },
  {
    "@id": "alma:library:DENTLOCKER",
    "@type": [ "http://www.loc.gov/mads/rdf/v1#Authority" ],
    "http://www.loc.gov/mads/rdf/v1#authoritativeLabel": [ { "@value": "DENTLOCKER" } ]
  },
  {
    "@id": "alma:library:DentalLib",
    "@type": [ "http://www.loc.gov/mads/rdf/v1#Authority" ],
    "http://www.loc.gov/mads/rdf/v1#authoritativeLabel": [ { "@value": "DentalLib" } ]
  },
  {
    "@id": "alma:library:EduCommons",
    "@type": [ "http://www.loc.gov/mads/rdf/v1#Authority" ],
    "http://www.loc.gov/mads/rdf/v1#authoritativeLabel": [ { "@value": "EduCommons" } ]
  },
  {
    "@id": "alma:library:EMPTY",
    "@type": [ "http://www.loc.gov/mads/rdf/v1#Authority" ],
    "http://www.loc.gov/mads/rdf/v1#authoritativeLabel": [ { "@value": "EMPTY" } ]
  },
  {
    "@id": "alma:library:FisherFAL",
    "@type": [ "http://www.loc.gov/mads/rdf/v1#Authority" ],
    "http://www.loc.gov/mads/rdf/v1#authoritativeLabel": [ { "@value": "FisherFAL" } ]
  },
  {
    "@id": "alma:library:HSPLib",
    "@type": [ "http://www.loc.gov/mads/rdf/v1#Authority" ],
    "http://www.loc.gov/mads/rdf/v1#authoritativeLabel": [ { "@value": "HSPLib" } ]
  },
  {
    "@id": "alma:library:PersonalCopy",
    "@type": [ "http://www.loc.gov/mads/rdf/v1#Authority" ],
    "http://www.loc.gov/mads/rdf/v1#authoritativeLabel": [ { "@value": "PersonalCopy" } ]
  },
  {
    "@id": "alma:library:ROTCLib",
    "@type": [ "http://www.loc.gov/mads/rdf/v1#Authority" ],
    "http://www.loc.gov/mads/rdf/v1#authoritativeLabel": [ { "@value": "ROTCLib" } ]
  },
  {
    "@id": "alma:library:KislakCntr",
    "@type": [ "http://www.loc.gov/mads/rdf/v1#Authority" ],
    "http://www.loc.gov/mads/rdf/v1#authoritativeLabel": [ { "@value": "KislakCntr" } ]
  },
  {
    "@id": "Libra",
    "@type": [ "http://www.loc.gov/mads/rdf/v1#Authority" ],
    "http://www.loc.gov/mads/rdf/v1#authoritativeLabel": [ { "@value": "Libra" } ]
  },
  {
    "@id": "alma:library:KatzLib",
    "@type": [ "http://www.loc.gov/mads/rdf/v1#Authority" ],
    "http://www.loc.gov/mads/rdf/v1#authoritativeLabel": [ { "@value": "KatzLib" } ]
  },
  {
    "@id": "alma:library:LippLib",
    "@type": [ "http://www.loc.gov/mads/rdf/v1#Authority" ],
    "http://www.loc.gov/mads/rdf/v1#authoritativeLabel": [ { "@value": "LippLib" } ]
  },
  {
    "@id": "alma:library:VPLOCKER",
    "@type": [ "http://www.loc.gov/mads/rdf/v1#Authority" ],
    "http://www.loc.gov/mads/rdf/v1#authoritativeLabel": [ { "@value": "VPLOCKER" } ]
  },
  {
    "@id": "alma:library:MPALib",
    "@type": [ "http://www.loc.gov/mads/rdf/v1#Authority" ],
    "http://www.loc.gov/mads/rdf/v1#authoritativeLabel": [ { "@value": "MPALib" } ]
  },
  {
    "@id": "alma:library:ArborLib",
    "@type": [ "http://www.loc.gov/mads/rdf/v1#Authority" ],
    "http://www.loc.gov/mads/rdf/v1#authoritativeLabel": [ { "@value": "ArborLib" } ]
  },
  {
    "@id": "alma:library:MuseumLib",
    "@type": [ "http://www.loc.gov/mads/rdf/v1#Authority" ],
    "http://www.loc.gov/mads/rdf/v1#authoritativeLabel": [ { "@value": "MuseumLib" } ]
  },
  {
    "@id": "alma:library:NonCircLib",
    "@type": [ "http://www.loc.gov/mads/rdf/v1#Authority" ],
    "http://www.loc.gov/mads/rdf/v1#authoritativeLabel": [ { "@value": "NonCircLib" } ]
  },
  {
    "@id": "alma:library:MusicLib",
    "@type": [ "http://www.loc.gov/mads/rdf/v1#Authority" ],
    "http://www.loc.gov/mads/rdf/v1#authoritativeLabel": [ { "@value": "MusicLib" } ]
  },
  {
    "@id": "alma:library:PAHospLib",
    "@type": [ "http://www.loc.gov/mads/rdf/v1#Authority" ],
    "http://www.loc.gov/mads/rdf/v1#authoritativeLabel": [ { "@value": "PAHospLib" } ]
  },
  {
    "@id": "alma:library:RES_SHARE",
    "@type": [ "http://www.loc.gov/mads/rdf/v1#Authority" ],
    "http://www.loc.gov/mads/rdf/v1#authoritativeLabel": [ { "@value": "RES_SHARE" } ]
  },
  {
    "@id": "alma:library:UnivArcLib",
    "@type": [ "http://www.loc.gov/mads/rdf/v1#Authority" ],
    "http://www.loc.gov/mads/rdf/v1#authoritativeLabel": [ { "@value": "UnivArcLib" } ]
  },
  {
    "@id": "alma:library:MuseArcLib",
    "@type": [ "http://www.loc.gov/mads/rdf/v1#Authority" ],
    "http://www.loc.gov/mads/rdf/v1#authoritativeLabel": [ { "@value": "MuseArcLib" } ]
  },
  {
    "@id": "alma:library:VanPeltLib",
    "@type": [ "http://www.loc.gov/mads/rdf/v1#Authority" ],
    "http://www.loc.gov/mads/rdf/v1#authoritativeLabel": [ { "@value": "VanPeltLib" } ]
  },
  {
    "@id": "alma:library:VetNBLib",
    "@type": [ "http://www.loc.gov/mads/rdf/v1#Authority" ],
    "http://www.loc.gov/mads/rdf/v1#authoritativeLabel": [ { "@value": "VetNBLib" } ]
  },
  {
    "@id": "alma:library:VetPennLib",
    "@type": [ "http://www.loc.gov/mads/rdf/v1#Authority" ],
    "http://www.loc.gov/mads/rdf/v1#authoritativeLabel": [ { "@value": "VetPennLib" } ]
  },
  {
    "@id": "alma:library:WeigleInfo",
    "@type": [ "http://www.loc.gov/mads/rdf/v1#Authority" ],
    "http://www.loc.gov/mads/rdf/v1#authoritativeLabel": [ { "@value": "WeigleInfo" } ]
  },
  {
    "@id": "alma:library:ZUnavailable",
    "@type": [ "http://www.loc.gov/mads/rdf/v1#Authority" ],
    "http://www.loc.gov/mads/rdf/v1#authoritativeLabel": [ { "@value": "ZUnavailable" } ]
  }
]